Metadata-Version: 2.1
Name: globalparams
Version: 1.0.2
Summary: parameters loader signelton
Home-page: https://github.com/ohadmen/paramspy
Author: Ohad Menashe
Author-email: ohad.men@gmail.com
License: UNKNOWN
Keywords: parameters,storage
Platform: UNKNOWN
Requires-Python: >=3.6
License-File: LICENSE
